Workbook

Sheet Instrucciones
A1: Plantilla de datos iniciales — Sistema de uniformes
A3: CÓMO LLENAR
A4: 1. Llenar las hojas en este orden: Colegios → Prendas → Tallas → Proveedores → Modelos → Conjuntos → Precios → Materiales → Consumo_por_prenda → Costo_reventa → Mano_de_obra → Gastos_mensuales → Inventario_prendas → Inventario_materiales.
A5: 2. Una fila = un registro. No combinar celdas, no dejar filas vacías entre datos y no cambiar los títulos de la fila 1.
A6: 3. La fila 2 de cada hoja (gris, empieza con EJ) es un EJEMPLO. Se puede dejar: el sistema ignora todo lo que empieza con EJ.
A7: 4. Pasar el mouse sobre el título de cada columna muestra qué va ahí. Donde aparece una flecha, elegir de la lista.
A8: 5. Los códigos (colegio, prenda, modelo, material, proveedor) se inventan una vez y luego se copian igual en las otras hojas. Usar MAYÚSCULAS, sin espacios ni tildes (ej. SANJOSE-CHOMPA-H).
A9: 6. Columnas verdes = automáticas. No escribir en ellas. Si dicen 'REVISAR' o 'NO EXISTE', hay un código mal escrito.
A10: 7. Decimales con punto (1.40). Fechas como dd/mm/aaaa. Dinero en dólares, sin el signo $.
A11: 8. Si un dato no se sabe, dejarlo vacío o escribir 'aproximado' en notas. Mejor aproximado que nada.
A12: 9. Responsable: RM o GL según a quién corresponde (RM = línea deportiva, GL = lo demás: sacos de lana, pantalones de tela, camisas...). Aparece solo en las hojas donde importa.
A14: QUÉ ES URGENTE
... A17: Al final (el día del conteo físico): Inventario_prendas e Inventario_materiales.

Sheet Colegios
A1: codigo_colegio | B1: nombre | C1: contacto | D1: telefono | E1: notas
A2: EJ-COL01 | B2: Unidad Educativa Hermano Miguel | C2: Si aplica | D2: Si aplica

Sheet Prendas
A1: codigo_prenda | B1: nombre | C1: categoria | D1: notas
A2: EJ-CHOMPA | B2: Chompa deportiva | C2: DEPORTIVO

Sheet Tallas
A1: talla | B1: orden | C1: tipo
A2: EJ-28 | B2: 1 | C2: NUMERICA

Sheet Proveedores
A1: codigo_proveedor | B1: nombre | C1: ruc | D1: telefono | E1: que_provee | F1: responsable | G1: notas
A2: EJ-PROV01 | B2: Nilotex | D2: 0988888888 | E2: Tela Vioto azul marino | F2: RM

Sheet Modelos
A1: codigo_modelo | B1: codigo_colegio | C1: codigo_prenda | D1: genero | E1: color | F1: tipo_abastecimiento | G1: codigo_proveedor | H1: talla_desde | I1: talla_hasta | J1: responsable | K1: notas | L1: revision
A2: EJ-COL01-CHOMPA | B2: EJ-COL01 | C2: EJ-CHOMPA | D2: UNISEX | E2: Azul marino | F2: FABRICADO | H2: EJ-28 | I2: EJ-42 | J2: RM | L2: =IF(B2="","",IF(AND(COUNTIF(Colegios!$A:$A,B2)>0,COUNTIF(Prendas!$A:$A,C2)>0),"OK","REVISAR CÓDIGOS")) -> OK
L3: =IF(B3="","",IF(AND(COUNTIF(Colegios!$A:$A,B3)>0,COUNTIF(Prendas!$A:$A,C3)>0),"OK","REVISAR CÓDIGOS"))
L4: =IF(B4="","",IF(AND(COUNTIF(Colegios!$A:$A,B4)>0,COUNTIF(Prendas!$A:$A,C4)>0),"OK","REVISAR CÓDIGOS"))
L5: =IF(B5="","",IF(AND(COUNTIF(Colegios!$A:$A,B5)>0,COUNTIF(Prendas!$A:$A,C5)>0),"OK","REVISAR CÓDIGOS"))
L6: =IF(B6="","",IF(AND(COUNTIF(Colegios!$A:$A,B6)>0,COUNTIF(Prendas!$A:$A,C6)>0),"OK","REVISAR CÓDIGOS"))
L7: =IF(B7="","",IF(AND(COUNTIF(Colegios!$A:$A,B7)>0,COUNTIF(Prendas!$A:$A,C7)>0),"OK","REVISAR CÓDIGOS"))
L8: =IF(B8="","",IF(AND(COUNTIF(Colegios!$A:$A,B8)>0,COUNTIF(Prendas!$A:$A,C8)>0),"OK","REVISAR CÓDIGOS"))
L9: =IF(B9="","",IF(AND(COUNTIF(Colegios!$A:$A,B9)>0,COUNTIF(Prendas!$A:$A,C9)>0),"OK","REVISAR CÓDIGOS"))
L10: =IF(B10="","",IF(AND(COUNTIF(Colegios!$A:$A,B10)>0,COUNTIF(Prendas!$A:$A,C10)>0),"OK","REVISAR CÓDIGOS"))
L11: =IF(B11="","",IF(AND(COUNTIF(Colegios!$A:$A,B11)>0,COUNTIF(Prendas!$A:$A,C11)>0),"OK","REVISAR CÓDIGOS"))
L12: =IF(B12="","",IF(AND(COUNTIF(Colegios!$A:$A,B12)>0,COUNTIF(Prendas!$A:$A,C12)>0),"OK","REVISAR CÓDIGOS"))
L13: =IF(B13="","",IF(AND(COUNTIF(Colegios!$A:$A,B13)>0,COUNTIF(Prendas!$A:$A,C13)>0),"OK","REVISAR CÓDIGOS"))
L14: =IF(B14="","",IF(AND(COUNTIF(Colegios!$A:$A,B14)>0,COUNTIF(Prendas!$A:$A,C14)>0),"OK","REVISAR CÓDIGOS"))
... L501: =IF(B501="","",IF(AND(COUNTIF(Colegios!$A:$A,B501)>0,COUNTIF(Prendas!$A:$A,C501)>0),"OK","REVISAR CÓDIGOS"))

Sheet Conjuntos
A1: codigo_conjunto | B1: nombre_conjunto | C1: codigo_modelo_pieza | D1: cantidad | E1: responsable | F1: notas
A2: EJ-COL01-EXTERIOR | B2: Exterior (chompa + pantalón) | C2: EJ-COL01-CHOMPA | D2: 1 | E2: RM

Sheet Precios
A1: codigo_producto | B1: talla | C1: precio_venta | D1: incluye_iva | E1: vigente_desde | F1: responsable | G1: notas
A2: EJ-COL01-CHOMPA | B2: 28 | C2: 15 | D2: SI | E2: 01/09/2026 | F2: RM

Sheet Materiales
A1: codigo_material | B1: nombre | C1: tipo | D1: unidad | E1: composicion | F1: color | G1: ancho_m | H1: codigo_proveedor | I1: precio_unitario | J1: fecha_precio | K1: responsable
A2: EJ-TELA01 | B2: Calentador azul marino | C2: TELA | D2: M | E2: 100% poliéster | F2: Azul marino | G2: 1.6 | H2: EJ-PROV01 | I2: 4.5 | J2: 15/08/2026 | K2: RM

Sheet Consumo_por_prenda
A1: codigo_modelo | B1: codigo_material | C1: talla | D1: cantidad | E1: unidad | F1: notas
A2: EJ-COL01-CHOMPA | B2: EJ-TELA01 | C2: EJ-8 | D2: 1.4 | E2: =IF(B2="","",IFERROR(INDEX(Materiales!$D:$D,MATCH(B2,Materiales!$A:$A,0)),"CÓDIGO NO EXISTE")) -> M | F2: aproximado
E3: =IF(B3="","",IFERROR(INDEX(Materiales!$D:$D,MATCH(B3,Materiales!$A:$A,0)),"CÓDIGO NO EXISTE"))
E4: =IF(B4="","",IFERROR(INDEX(Materiales!$D:$D,MATCH(B4,Materiales!$A:$A,0)),"CÓDIGO NO EXISTE"))
E5: =IF(B5="","",IFERROR(INDEX(Materiales!$D:$D,MATCH(B5,Materiales!$A:$A,0)),"CÓDIGO NO EXISTE"))
E6: =IF(B6="","",IFERROR(INDEX(Materiales!$D:$D,MATCH(B6,Materiales!$A:$A,0)),"CÓDIGO NO EXISTE"))
E7: =IF(B7="","",IFERROR(INDEX(Materiales!$D:$D,MATCH(B7,Materiales!$A:$A,0)),"CÓDIGO NO EXISTE"))
E8: =IF(B8="","",IFERROR(INDEX(Materiales!$D:$D,MATCH(B8,Materiales!$A:$A,0)),"CÓDIGO NO EXISTE"))
E9: =IF(B9="","",IFERROR(INDEX(Materiales!$D:$D,MATCH(B9,Materiales!$A:$A,0)),"CÓDIGO NO EXISTE"))
E10: =IF(B10="","",IFERROR(INDEX(Materiales!$D:$D,MATCH(B10,Materiales!$A:$A,0)),"CÓDIGO NO EXISTE"))
E11: =IF(B11="","",IFERROR(INDEX(Materiales!$D:$D,MATCH(B11,Materiales!$A:$A,0)),"CÓDIGO NO EXISTE"))
E12: =IF(B12="","",IFERROR(INDEX(Materiales!$D:$D,MATCH(B12,Materiales!$A:$A,0)),"CÓDIGO NO EXISTE"))
E13: =IF(B13="","",IFERROR(INDEX(Materiales!$D:$D,MATCH(B13,Materiales!$A:$A,0)),"CÓDIGO NO EXISTE"))
E14: =IF(B14="","",IFERROR(INDEX(Materiales!$D:$D,MATCH(B14,Materiales!$A:$A,0)),"CÓDIGO NO EXISTE"))
... E501: =IF(B501="","",IFERROR(INDEX(Materiales!$D:$D,MATCH(B501,Materiales!$A:$A,0)),"CÓDIGO NO EXISTE"))

Sheet Costo_reventa
A1: codigo_modelo | B1: talla | C1: costo_unitario | D1: codigo_proveedor | E1: fecha | F1: responsable | G1: notas
A2: EJ-MEDIAS | C2: 1.2 | D2: EJ-PROV01 | E2: 10/08/2026 | F2: GL

Sheet Mano_de_obra
A1: codigo_prenda | B1: operacion | C1: como_se_paga | D1: valor | E1: responsable | F1: notas
A2: EJ-CHOMPA | B2: CONFECCION | C2: SUELDO_MENSUAL | D2: 2.5 | E2: RM

Sheet Gastos_mensuales
A1: concepto | B1: monto_mensual | C1: responsable | D1: notas
A2: Arriendo del local
A3: Arriendo del taller
A4: Luz
A5: Agua
A6: Internet y teléfono
A7: Mantenimiento de máquinas
A8: Repuestos (agujas, aceite, etc.)
A9: Transporte y fletes
A10: Bolsas y empaques
A11: Sueldos fijos (que no están en Mano_de_obra)
A12: Otros

Sheet Inventario_prendas
A1: codigo_modelo | B1: talla | C1: cantidad | D1: ubicacion | E1: responsable | F1: fecha_conteo | G1: contado_por | H1: notas
A2: EJ-COL01-CHOMPA | B2: EJ-8 | C2: 12 | D2: LOCAL | E2: RM | F2: 15/10/2026

Sheet Inventario_materiales
A1: codigo_material | B1: cantidad | C1: unidad | D1: ubicacion | E1: responsable | F1: fecha_conteo | G1: contado_por | H1: notas
A2: EJ-TELA01 | B2: 35.5 | C2: =IF(A2="","",IFERROR(INDEX(Materiales!$D:$D,MATCH(A2,Materiales!$A:$A,0)),"CÓDIGO NO EXISTE")) -> M | D2: TALLER | E2: RM | F2: 15/10/2026
C3: =IF(A3="","",IFERROR(INDEX(Materiales!$D:$D,MATCH(A3,Materiales!$A:$A,0)),"CÓDIGO NO EXISTE"))
C4: =IF(A4="","",IFERROR(INDEX(Materiales!$D:$D,MATCH(A4,Materiales!$A:$A,0)),"CÓDIGO NO EXISTE"))
C5: =IF(A5="","",IFERROR(INDEX(Materiales!$D:$D,MATCH(A5,Materiales!$A:$A,0)),"CÓDIGO NO EXISTE"))
C6: =IF(A6="","",IFERROR(INDEX(Materiales!$D:$D,MATCH(A6,Materiales!$A:$A,0)),"CÓDIGO NO EXISTE"))
C7: =IF(A7="","",IFERROR(INDEX(Materiales!$D:$D,MATCH(A7,Materiales!$A:$A,0)),"CÓDIGO NO EXISTE"))
C8: =IF(A8="","",IFERROR(INDEX(Materiales!$D:$D,MATCH(A8,Materiales!$A:$A,0)),"CÓDIGO NO EXISTE"))
C9: =IF(A9="","",IFERROR(INDEX(Materiales!$D:$D,MATCH(A9,Materiales!$A:$A,0)),"CÓDIGO NO EXISTE"))
C10: =IF(A10="","",IFERROR(INDEX(Materiales!$D:$D,MATCH(A10,Materiales!$A:$A,0)),"CÓDIGO NO EXISTE"))
C11: =IF(A11="","",IFERROR(INDEX(Materiales!$D:$D,MATCH(A11,Materiales!$A:$A,0)),"CÓDIGO NO EXISTE"))
C12: =IF(A12="","",IFERROR(INDEX(Materiales!$D:$D,MATCH(A12,Materiales!$A:$A,0)),"CÓDIGO NO EXISTE"))
C13: =IF(A13="","",IFERROR(INDEX(Materiales!$D:$D,MATCH(A13,Materiales!$A:$A,0)),"CÓDIGO NO EXISTE"))
C14: =IF(A14="","",IFERROR(INDEX(Materiales!$D:$D,MATCH(A14,Materiales!$A:$A,0)),"CÓDIGO NO EXISTE"))
... C501: =IF(A501="","",IFERROR(INDEX(Materiales!$D:$D,MATCH(A501,Materiales!$A:$A,0)),"CÓDIGO NO EXISTE"))

Sheet Listas
A1: RESPONSABLE | B1: SI_NO | C1: GENERO | D1: ABASTECIMIENTO | E1: TIPO_MATERIAL | F1: UNIDAD | G1: CATEGORIA | H1: TIPO_TALLA | I1: COMO_SE_PAGA | J1: UBICACION
A2: RM | B2: SI | C2: HOMBRE | D2: FABRICADO | E2: TELA | F2: M | G2: ESCOLAR | H2: NUMERICA | I2: POR_PRENDA | J2: LOCAL
A3: GL | B3: NO | C3: MUJER | D3: COMPRADO | E3: INSUMO | F3: UNIDAD | G3: DEPORTIVO | H3: LETRA | I3: SUELDO_MENSUAL | J3: TALLER
C4: UNISEX | E4: PRENDA_BASE | F4: KG | G4: OTRO | J4: BODEGA
E5: OTRO | F5: ROLLO | J5: OTRO
F6: CONO
